AtLog/__init__.py
AtLog/atlog.py
AtLog/main.py
AtLog-1.0.0.dist-info/LICENSE
AtLog-1.0.0.dist-info/METADATA
AtLog-1.0.0.dist-info/WHEEL
AtLog-1.0.0.dist-info/top_level.txt
AtLog-1.0.0.dist-info/RECORD
