Metadata-Version: 2.1
Name: AtLog
Version: 1.0.0
Summary: Decorator for logging functions and coroutines
Home-page: https://github.com/Jlobblet/AtLog
Author: John Blundell
Author-email: jlobblet-github@gmx.co.uk
License: UNKNOWN
Project-URL: Bug Tracker, https://github.com/Jlobblet/AtLog/issues
Platform: UNKNOWN
Classifier: Programming Language :: Python :: 3
Classifier: License :: OSI Approved :: MIT License
Classifier: Operating System :: OS Independent
Requires-Python: >=3.6
License-File: LICENSE
